Metadata-Version: 2.1
Name: firestore-collections
Version: 0.2.2
Summary: Simple Firestore collection definitions and queries using pydantic schemas and Firestore query API.
Home-page: https://github.com/LasseRegin/firestore-collections
Author: Lasse Regin Nielsen
Author-email: lasseregin@gmail.com
License: UNKNOWN
Platform: UNKNOWN
Classifier: Programming Language :: Python :: 3
Classifier: License :: OSI Approved :: MIT License
Classifier: Operating System :: OS Independent
Requires-Python: >=3.6
